allennlp_wordsplitter_corenlp/__init__.py
allennlp_wordsplitter_corenlp/_version.py
allennlp_wordsplitter_corenlp/version.py
allennlp_wordsplitter_corenlp/wordspliters.py
allennlp_wordsplitter_corenlp-0.1a2.dist-info/AUTHORS.md
allennlp_wordsplitter_corenlp-0.1a2.dist-info/METADATA
allennlp_wordsplitter_corenlp-0.1a2.dist-info/WHEEL
allennlp_wordsplitter_corenlp-0.1a2.dist-info/namespace_packages.txt
allennlp_wordsplitter_corenlp-0.1a2.dist-info/top_level.txt
allennlp_wordsplitter_corenlp-0.1a2.dist-info/RECORD
