Metadata-Version: 2.1
Name: allennlp-wordsplitter-corenlp
Version: 0.1a2
Summary: CoreNLP word splitter for AllenNLP
Home-page: https://github.com/tanbro/allennlp_wordsplitter_corenlp
Author: liu xue yan
Author-email: liu_xue_yan@foxmail.com
License: UNKNOWN
Platform: UNKNOWN
Requires-Dist: allennlp (<0.9,>=0.7)
